graphixlite/Application.py
graphixlite/ApplicationMeta.py
graphixlite/CollisionEngine.py
graphixlite/PlatformMeta.py
graphixlite/__init__.py
graphixlite/drawables/Line.py
graphixlite/drawables/Pixel.py
graphixlite/objects/Drawable.py
graphixlite/objects/GraphicOutput.py
graphixlite/objects/GraphicParent.py
graphixlite/objects/View.py
graphixlite/objects/Window.py
graphixlite/outputs/SDLParent.py
graphixlite/outputs/SDLWindow.py
graphixlite/outputs/WebParent.py
graphixlite/outputs/WebWindow.py
graphixlite-0.0.1rc0.dist-info/LICENSE
graphixlite-0.0.1rc0.dist-info/METADATA
graphixlite-0.0.1rc0.dist-info/WHEEL
graphixlite-0.0.1rc0.dist-info/top_level.txt
graphixlite-0.0.1rc0.dist-info/RECORD
